setup.py
inquiry/__init__.py
inquiry/figure.py
inquiry/garden.py
inquiry/helpers.py
inquiry/inquiry.py
inquiry/navigator.py
inquiry/query.py
inquiry/results.py
inquiry/validators.py
inquiry.egg-info/PKG-INFO
inquiry.egg-info/SOURCES.txt
inquiry.egg-info/dependency_links.txt
inquiry.egg-info/not-zip-safe
inquiry.egg-info/requires.txt
inquiry.egg-info/top_level.txt