Metadata-Version: 1.1
Name: inquiry
Version: 0.0.2
Summary: psql query generator
Home-page: https://github.com/tasks/inquiry
Author: @stevepeak
Author-email: steve@stevepeak.net
License: Apache v2
Platform: UNKNOWN
Classifier: Development Status :: 4 - Beta
Classifier: License :: OSI Approved :: Apache Software License
